easyrec/__init__.py
easyrec/datasets/__init__.py
easyrec/datasets/criteo.py
easyrec/datasets/data_process.py
easyrec/datasets/movielen.py
easyrec/layers/__init__.py
easyrec/layers/activation.py
easyrec/layers/attention_sequence_pooling_layer.py
easyrec/layers/dense.py
easyrec/layers/get_input_layer.py
easyrec/layers/local_activation_unit.py
easyrec/layers/residual_block.py
easyrec/layers/sequence_pooling.py
easyrec/models/__init__.py
easyrec/models/base.py
easyrec/models/deepcrossing.py
easyrec/models/deepfm.py
easyrec/models/din.py
easyrec/models/sequence_base.py
easyrec/models/wide_deep.py
easyrec/utils/__init__.py
easyrec/utils/bulid.py
easyrec/utils/callbacks.py
easyrec/utils/feature.py
easyrec-0.1.0b0.dist-info/LICENSE
easyrec-0.1.0b0.dist-info/METADATA
easyrec-0.1.0b0.dist-info/WHEEL
easyrec-0.1.0b0.dist-info/top_level.txt
easyrec-0.1.0b0.dist-info/RECORD
