Metadata-Version: 2.1
Name: easyrec
Version: 0.1.0b0
Summary: deep learning frame for recommendation algorithm
Home-page: https://github.com/yinpu/easyrec
Author: yinpu
Author-email: 741456392@163.com
License: MIT
Download-URL: https://github.com/yinpu/easyrec/tags
Keywords: deep learning,torch,tensor,pytorch
Platform: UNKNOWN
Classifier: License :: OSI Approved :: Apache Software License
Classifier: Operating System :: OS Independent
Classifier: Intended Audience :: Developers
Classifier: Intended Audience :: Education
Classifier: Intended Audience :: Science/Research
Classifier: Programming Language :: Python :: 3.5
Classifier: Programming Language :: Python :: 3.6
Classifier: Programming Language :: Python :: 3.7
Classifier: Topic :: Scientific/Engineering
Classifier: Topic :: Scientific/Engineering :: Artificial Intelligence
Classifier: Topic :: Software Development
Classifier: Topic :: Software Development :: Libraries
Classifier: Topic :: Software Development :: Libraries :: Python Modules
Requires-Python: >=3.5.*
Requires-Dist: torch (>=1.1.0)
Requires-Dist: tqdm
Requires-Dist: sklearn
Requires-Dist: tensorflow
